pymaml/__init__.py
pymaml/date_funcs.py
pymaml/maml.py
pymaml/model_v1p0.py
pymaml/model_v1p1.py
pymaml/parse.py
pymaml/read.py
pymaml/schemas/v1p0.json
pymaml/schemas/v1p1.json
pymaml-0.6.3.dist-info/WHEEL
pymaml-0.6.3.dist-info/entry_points.txt
pymaml-0.6.3.dist-info/METADATA
pymaml-0.6.3.dist-info/RECORD
