Metadata-Version: 2.4
Name: pymaml
Version: 0.6.3
Summary: Python reader, writer and validator for Meta yAML (MAML).
Author: TrystanScottLambert
Author-email: TrystanScottLambert <trystanscottlambert@gmail.com>
License-Expression: MIT
Requires-Dist: astropy>=7.1.0
Requires-Dist: pandas>=2.3.2
Requires-Dist: pyaml>=25.7.0
Requires-Dist: rich>=14.1.0
Requires-Dist: twine>=6.1.0
Requires-Dist: polars>=1.35.1
Requires-Python: >=3.11
